black_mamba/__init__.py
black_mamba/auth/__init__.py
black_mamba/compilation/compiled_files/migration_sample.py
black_mamba/compilation/vyper_compiler.py
black_mamba/constants.py
black_mamba/contract/__init__.py
black_mamba/contract/build_contract.py
black_mamba/contract/contract.py
black_mamba/deploy/__init__.py
black_mamba/epm/__init__.py
black_mamba/epm/manifest.py
black_mamba/epm/package_manager.py
black_mamba/etherscan/accounts.py
black_mamba/etherscan/tokens.py
black_mamba/initialization/init.py
black_mamba/initialization/init_files/settings_sample.py
black_mamba/mamba_cli.py
black_mamba/mnemonic/__init__.py
black_mamba/server/geth_dev_server.py
black_mamba/server/server_files/genesis.json
black_mamba/server/server_files/private_key.json
black_mamba/settings_directory.py
black_mamba/testlib/__init__.py
black_mamba/testlib/test_with_contracts.py
black_mamba-0.6.4.dist-info/entry_points.txt
black_mamba-0.6.4.dist-info/LICENSE
black_mamba-0.6.4.dist-info/WHEEL
black_mamba-0.6.4.dist-info/METADATA
black_mamba-0.6.4.dist-info/RECORD
