Metadata-Version: 2.1
Name: black-mamba
Version: 0.6.4
Summary: Development framework to write, test and deploy smart contracts written in Vyper and Solidity. It has integrated web3.py support.
Home-page: https://mamba.black
License: LGPL-3.0
Keywords: blockchain
Author: Arjuna Sky Kok
Author-email: arjuna@mamba.black
Requires-Python: >=3.6,<4.0
Classifier: License :: OSI Approved :: GNU Lesser General Public License v3 (LGPLv3)
Classifier: Programming Language :: Python :: 3
Classifier: Programming Language :: Python :: 3.6
Classifier: Programming Language :: Python :: 3.7
Classifier: Programming Language :: Python :: 3.8
Classifier: Topic :: Software Development :: Build Tools
Classifier: Topic :: Software Development :: Libraries :: Python Modules
Requires-Dist: eth-tester (==0.5.0b4)
Requires-Dist: py-evm (==0.4.0a4)
Requires-Dist: pytest (==6.2.1)
Requires-Dist: pytest-mock (==3.5.1)
Requires-Dist: vyper (==0.2.12)
Requires-Dist: web3 (==5.19.0)
Project-URL: Repository, https://github.com/arjunaskykok/mamba
